{
  "companies": [
    {
      "name": "CityBee",
      "cars": [
        {
          "car_model": "All cars",
          "start_fee": 0.44,
          "time_rates": {
            "minute": 0.14,
            "hour": 6.19,
            "day": 22.99
          },
          "distance_rate": 0.29,
          "included_distance": 0,
          "trip_packages": [
            {
              "name": "1 D + 50 KM",
              "duration": 1440,
              "included_distance": 50,
              "price": 29.9
            },
            {
              "name": "1 H + 10 KM",
              "duration": 60,
              "included_distance": 10,
              "price": 5.89
            },
            {
              "name": "2 D + 320 KM ",
              "duration": 2880,
              "included_distance": 320,
              "price": 99.0
            },
            {
              "name": "30 MIN. + 5 KM",
              "duration": 30,
              "included_distance": 5,
              "price": 5.29
            },
            {
              "name": "30 MIN. + 10 KM",
              "duration": 30,
              "included_distance": 10,
              "price": 6.29
            },
            {
              "name": "1 H + 25 KM",
              "duration": 60,
              "included_distance": 25,
              "price": 12.09
            },
            {
              "name": "2 H + 20 KM",
              "duration": 120,
              "included_distance": 20,
              "price": 15.69
            },
            {
              "name": "2 H + 35 KM",
              "duration": 120,
              "included_distance": 35,
              "price": 19.69
            },
            {
              "name": "2 H + 45 KM",
              "duration": 120,
              "included_distance": 45,
              "price": 22.29
            },
            {
              "name": "3 H + 15 KM",
              "duration": 180,
              "included_distance": 15,
              "price": 19.69
            },
            {
              "name": "3 H + 30 KM",
              "duration": 180,
              "included_distance": 30,
              "price": 23.29
            },
            {
              "name": "3 H + 75 KM",
              "duration": 180,
              "included_distance": 75,
              "price": 34.89
            },
            {
              "name": "4 H + 40 KM",
              "duration": 240,
              "included_distance": 40,
              "price": 30.69
            },
            {
              "name": "9 H + 100 KM",
              "duration": 540,
              "included_distance": 100,
              "price": 44.29
            },
            {
              "name": "9 H + 250 KM",
              "duration": 540,
              "included_distance": 250,
              "price": 84.09
            },
            {
              "name": "12 H + 60 KM",
              "duration": 720,
              "included_distance": 60,
              "price": 34.69
            },
            {
              "name": "12 H + 150 KM",
              "duration": 720,
              "included_distance": 150,
              "price": 57.49
            },
            {
              "name": "1 D + 25 KM",
              "duration": 1440,
              "included_distance": 25,
              "price": 24.9
            },
            {
              "name": "1 D + 75 KM",
              "duration": 1440,
              "included_distance": 75,
              "price": 34.9
            },
            {
              "name": "1 D + 100 KM",
              "duration": 1440,
              "included_distance": 100,
              "price": 39.9
            },
            {
              "name": "1 D + 150 KM",
              "duration": 1440,
              "included_distance": 150,
              "price": 57.4
            },
            {
              "name": "1 D + 250 KM",
              "duration": 1440,
              "included_distance": 250,
              "price": 83.9
            },
            {
              "name": "1 D + 350 KM",
              "duration": 1440,
              "included_distance": 350,
              "price": 110.9
            },
            {
              "name": "2 D + 50 KM",
              "duration": 2880,
              "included_distance": 50,
              "price": 48.9
            },
            {
              "name": "2 D + 100 KM",
              "duration": 2880,
              "included_distance": 100,
              "price": 61.9
            },
            {
              "name": "2 D + 250 KM",
              "duration": 2880,
              "included_distance": 250,
              "price": 101.4
            },
            {
              "name": "2 D + 400 KM",
              "duration": 2880,
              "included_distance": 400,
              "price": 141.9
            },
            {
              "name": "3 D + 100 KM",
              "duration": 4320,
              "included_distance": 100,
              "price": 79.4
            },
            {
              "name": "3 D + 175 KM",
              "duration": 4320,
              "included_distance": 175,
              "price": 98.9
            },
            {
              "name": "3 D + 200 KM",
              "duration": 4320,
              "included_distance": 200,
              "price": 105.4
            },
            {
              "name": "3 D + 300 KM",
              "duration": 4320,
              "included_distance": 300,
              "price": 132.4
            },
            {
              "name": "3 D + 500 KM",
              "duration": 4320,
              "included_distance": 500,
              "price": 185.9
            },
            {
              "name": "5 D + 150 KM",
              "duration": 7200,
              "included_distance": 150,
              "price": 140.4
            },
            {
              "name": "5 D + 250 KM",
              "duration": 7200,
              "included_distance": 250,
              "price": 166.9
            },
            {
              "name": "5 D + 450 KM",
              "duration": 7200,
              "included_distance": 450,
              "price": 220.4
            },
            {
              "name": "7 D + 200 KM",
              "duration": 10080,
              "included_distance": 200,
              "price": 174.4
            },
            {
              "name": "7 D + 400 KM",
              "duration": 10080,
              "included_distance": 400,
              "price": 227.9
            },
            {
              "name": "7 D + 600 KM",
              "duration": 10080,
              "included_distance": 600,
              "price": 282.4
            },
            {
              "name": "7 D + 900 KM",
              "duration": 10080,
              "included_distance": 900,
              "price": 364.9
            },
            {
              "name": "14 D + 600 KM",
              "duration": 20160,
              "included_distance": 600,
              "price": 401.9
            },
            {
              "name": "14 D + 1000 KM",
              "duration": 20160,
              "included_distance": 1000,
              "price": 511.9
            },
            {
              "name": "28 D + 1800 KM",
              "duration": 40320,
              "included_distance": 1800,
              "price": 973.4
            },
            {
              "name": "28 D + 2500 KM",
              "duration": 40320,
              "included_distance": 2500,
              "price": 1175.9
            }
          ],
          "tags": []
        }
      ]
    },
    {
      "name": "CarGuru",
      "cars": [
        {
          "car_model": "Toyota Yaris, Nissan Juke",
          "start_fee": 0.99,
          "time_rates": {
            "minute": 0.21,
            "1 hour": 8,
            "3 hour": 21.17,
            "1 day": 35.99,
            "2 day": 68.37,
            "3 day": 100.76,
            "7 day": 226.71,
            "14 day": 408.08,
            "30 day": 816.15
          },
          "distance_rate": 0.21,
          "included_distance": 100,
          "trip_packages": null,
          "tags": ["LIM"]
        },
        {
          "car_model": "Toyota Corolla",
          "start_fee": 0.99,
          "time_rates": {
            "minute": 0.27,
            "1 hour": 8,
            "3 hour": 27.22,
            "1 day": 49.27,
            "2 day": 93.61,
            "3 day": 124.15,
            "7 day": 248.31,
            "14 day": 446.95,
            "30 day": 893.90
          },
          "distance_rate": 0.23,
          "included_distance": 100,
          "trip_packages": null,
          "tags": ["LIM"]
        },
        {
          "car_model": "Toyota C-HR, Nissan Qashqai",
          "start_fee": 0.99,
          "time_rates": {
            "minute": 0.28,
            "1 hour": 8,
            "3 hour": 29.22,
            "1 day": 52.68,
            "2 day": 100.09,
            "3 day": 132.76,
            "7 day": 265.51,
            "14 day": 477.92,
            "30 day": 955.84
          },
          "distance_rate": 0.24,
          "included_distance": 100,
          "trip_packages": null,
          "tags": ["LIM"]
        },
        {
          "car_model": "Tesla Model 3 SR/LR",
          "start_fee": 0.99,
          "time_rates": {
            "minute": 0.33,
            "1 hour": 8,
            "3 hour": 33.26,
            "1 day": 59.55,
            "2 day": 113.14,
            "3 day": 166.74,
            "7 day": 375.16,
            "14 day": 582.97,
            "30 day": 1165.93
          },
          "distance_rate": 0.25,
          "included_distance": 100,
          "trip_packages": null,
          "tags": ["EV", "LIM"]
        },
        {
          "car_model": "Tesla Model 3 P, Model Y SR/LR",
          "start_fee": 0.99,
          "time_rates": {
            "minute": 0.37,
            "1 hour": 8,
            "3 hour": 37.30,
            "1 day": 68.40,
            "2 day": 129.97,
            "3 day": 191.53,
            "7 day": 430.94,
            "14 day": 660.70,
            "30 day": 1321.39
          },
          "distance_rate": 0.25,
          "included_distance": 100,
          "trip_packages": null,
          "tags": ["EV", "LIM"]
        },
        {
          "car_model": "Toyota C-HR (MESA)",
          "start_fee": 0.99,
          "time_rates": {
            "minute": 0.09,
            "1 day": 18.99
          },
          "distance_rate": 0.29,
          "included_distance": 0,
          "trip_packages": null,
          "tags": null
        },
        {
          "car_model": "(Special) Toyota Yaris, Nissan Juke",
          "start_fee": 0,
          "time_rates": {
            "1 day": 19.97
          },
          "distance_rate": 0.12,
          "included_distance": 0,
          "trip_packages": null,
          "tags": null
        },
        {
          "car_model": "(Special) Toyota Corolla",
          "start_fee": 0,
          "time_rates": {
            "1 day": 21.63
          },
          "distance_rate": 0.12,
          "included_distance": 0,
          "trip_packages": null,
          "tags": null
        },
        {
          "car_model": "(Sepcial) Toyota C-HR, Nissan Qashqai",
          "start_fee": 0,
          "time_rates": {
            "1 day": 24.97
          },
          "distance_rate": 0.12,
          "included_distance": 0,
          "trip_packages": null,
          "tags": null
        },
        {
          "car_model": "(Special) Tesla Model 3 SR/LR",
          "start_fee": 0,
          "time_rates": {
            "1 day": 29.97
          },
          "distance_rate": 0.12,
          "included_distance": 0,
          "trip_packages": null,
          "tags": ["EV"]
        },
        {
          "car_model": "(Special) Tesla Model 3 P, Tesla Model Y SR/LR",
          "start_fee": 0,
          "time_rates": {
            "1 day": 33.30
          },
          "distance_rate": 0.12,
          "included_distance": 0,
          "trip_packages": null,
          "tags": ["EV"]
        }
      ]
    },
    {
      "name": "Bolt",
      "cars": [
        {
          "car_model": "Peugeot 208, Toyota Yaris",
          "start_fee": 0,
          "time_rates": {
            "minute": 0.12,
            "hour": 4.90,
            "day": 19.90
          },
          "distance_rate": 0.27,
          "included_distance": 0,
          "trip_packages": null,
          "tags": []
        },
        {
          "car_model": "Toyota Corolla, Toyota Yaris Cross, Audi A3, VW Golf",
          "start_fee": 0,
          "time_rates": {
            "minute": 0.13,
            "hour": 5.90,
            "day": 20.90
          },
          "distance_rate": 0.28,
          "included_distance": 0,
          "trip_packages": null,
          "tags": []
        },
        {
          "car_model": "Toyota C-HR, Peugeot 2008, Audi Q2, VW T-Cross",
          "start_fee": 0,
          "time_rates": {
            "minute": 0.14,
            "hour": 5.90,
            "day": 21.90
          },
          "distance_rate": 0.29,
          "included_distance": 0,
          "trip_packages": null,
          "tags": []
        },
        {
          "car_model": "Audi A4/A5",
          "start_fee": 0,
          "time_rates": {
            "minute": 0.16,
            "hour": 9.90,
            "day": 45.90
          },
          "distance_rate": 0.29,
          "included_distance": 0,
          "trip_packages": null,
          "tags": []
        },
        {
          "car_model": "BMW 4 Series Cabrio",
          "start_fee": 0,
          "time_rates": {
            "minute": 0.32,
            "hour": 19.90,
            "day": 79.90
          },
          "distance_rate": 0.31,
          "included_distance": 0,
          "trip_packages": null,
          "tags": []
        },
        {
          "car_model": "VW ID Buzz",
          "start_fee": 0,
          "time_rates": {
            "minute": 0.21,
            "hour": 11.90,
            "day": 59.90
          },
          "distance_rate": 0.29,
          "included_distance": 0,
          "trip_packages": null,
          "tags": []
        },
        {
          "car_model": "VW Tiguan",
          "start_fee": 0,
          "time_rates": {
            "minute": 0.15,
            "hour": 6.90,
            "day": 27.90
          },
          "distance_rate": 0.29,
          "included_distance": 0,
          "trip_packages": null,
          "tags": []
        }
      ]
    },
    {
      "name": "Avis Now",
      "cars": [
        {
          "car_model": "Cupra Born",
          "start_fee": 0,
          "time_rates": {
            "minute": 0.12,
            "hour": 4.99,
            "day": 24.5
          },
          "distance_rate": 0.22,
          "included_distance": 0,
          "trip_packages": null,
          "tags": [
            "EV"
          ]
        }
      ]
    },
    {
      "name": "Sixt/Avis/Hertz/Europcar",
      "cars": [
        {
          "car_model": "Compact car",
          "start_fee": 0,
          "time_rates": {
            "day": 45
          },
          "distance_rate": 0.09,
          "included_distance": 0,
          "trip_packages": null,
          "tags": []
        }
      ]
    }
  ]
}